codeallybasic/BasePubSubEngine.py
codeallybasic/Basic.py
codeallybasic/Common.py
codeallybasic/ConfigurationLocator.py
codeallybasic/ConfigurationProperties.py
codeallybasic/Dimensions.py
codeallybasic/DynamicConfiguration.py
codeallybasic/Environment.py
codeallybasic/MinMax.py
codeallybasic/PassThroughInterpolation.py
codeallybasic/Position.py
codeallybasic/ResourceManager.py
codeallybasic/SecureConversions.py
codeallybasic/SemanticVersion.py
codeallybasic/SingletonV3.py
codeallybasic/UnitTestBase.py
codeallybasic/__init__.py
codeallybasic/_version.py
codeallybasic/py.typed
codeallybasic-1.30.0.dist-info/licenses/LICENSE
codeallybasic-1.30.0.dist-info/METADATA
codeallybasic-1.30.0.dist-info/WHEEL
codeallybasic-1.30.0.dist-info/top_level.txt
codeallybasic-1.30.0.dist-info/RECORD
