Metadata-Version: 2.4
Name: codeallybasic
Version: 1.30.0
Summary: Humberto`s Basic Common Code
Author-email: "Humberto A. Sanchez II" <Humberto.A.Sanchez.II@gmail.com>
Maintainer-email: "Humberto A. Sanchez II" <Humberto.A.Sanchez.II@gmail.com>
License-Expression: AGPL-1.0-or-later
Project-URL: Repository, https://github.com/hasii2011/code-ally-basic
Keywords: pyut,python
Classifier: Programming Language :: Python
Classifier: Intended Audience :: Developers
Classifier: Operating System :: MacOS :: MacOS X
Classifier: Topic :: Software Development :: Libraries :: Python Modules
License-File: LICENSE
Requires-Dist: Deprecated>=1.2.18
Requires-Dist: Pypubsub==4.0.3
Provides-Extra: test
Requires-Dist: html-testRunner~=1.2.1; extra == "test"
Requires-Dist: mypy==1.14.1; extra == "test"
Requires-Dist: mypy-extensions==1.1.0; extra == "test"
Requires-Dist: typing_extensions==4.10.0; extra == "test"
Requires-Dist: types-Deprecated==1.2.9.20240311; extra == "test"
Requires-Dist: buildlackey==1.8.2; extra == "test"
Provides-Extra: deploy
Requires-Dist: wheel==0.45.1; extra == "deploy"
Requires-Dist: setuptools==75.7.0; extra == "deploy"
Requires-Dist: twine==6.1.0; extra == "deploy"
Requires-Dist: build==1.2.2.post1; extra == "deploy"
Requires-Dist: pkginfo==1.12.1.2; extra == "deploy"
Dynamic: license-file
